kernel/__init__.py
kernel/base.py
kernel/fun.py
kernel/utils.py
convolution_kernels-0.1.dist-info/METADATA
convolution_kernels-0.1.dist-info/WHEEL
convolution_kernels-0.1.dist-info/top_level.txt
convolution_kernels-0.1.dist-info/RECORD
